PasteScript-3.6.0-py3.11-nspkg.pth
paste/script/__init__.py
paste/script/appinstall.py
paste/script/bool_optparse.py
paste/script/cgi_server.py
paste/script/checkperms.py
paste/script/cherrypy_server.py
paste/script/command.py
paste/script/copydir.py
paste/script/create_distro.py
paste/script/default_sysconfig.py
paste/script/entrypoints.py
paste/script/epdesc.py
paste/script/exe.py
paste/script/filemaker.py
paste/script/flup_server.py
paste/script/grep.py
paste/script/help.py
paste/script/interfaces.py
paste/script/pluginlib.py
paste/script/request.py
paste/script/serve.py
paste/script/templates.py
paste/script/testapp.py
paste/script/twisted_web2_server.py
paste/script/wsgiutils_server.py
paste/script/paster-templates/basic_package/setup.cfg
paste/script/paster-templates/basic_package/setup.py_tmpl
paste/script/paster-templates/basic_package/+package+/__init__.py
paste/script/util/__init__.py
paste/script/util/logging_config.py
paste/script/util/secret.py
PasteScript-3.6.0.dist-info/AUTHORS
PasteScript-3.6.0.dist-info/METADATA
PasteScript-3.6.0.dist-info/WHEEL
PasteScript-3.6.0.dist-info/entry_points.txt
PasteScript-3.6.0.dist-info/namespace_packages.txt
PasteScript-3.6.0.dist-info/top_level.txt
PasteScript-3.6.0.dist-info/RECORD
