Metadata-Version: 2.1
Name: PasteScript
Version: 3.6.0
Summary: A pluggable command-line frontend, including commands to setup package file layouts
Home-page: https://pastescript.readthedocs.io/
Author: Ian Bicking
Author-email: ianb@colorstudy.com
License: MIT
Keywords: web wsgi setuptools framework command-line setup
Classifier: Development Status :: 6 - Mature
Classifier: Intended Audience :: Developers
Classifier: License :: OSI Approved :: MIT License
Classifier: Programming Language :: Python :: 3
Classifier: Programming Language :: Python :: 3.7
Classifier: Programming Language :: Python :: 3.8
Classifier: Programming Language :: Python :: 3.9
Classifier: Programming Language :: Python :: 3.10
Classifier: Programming Language :: Python :: 3.11
Classifier: Programming Language :: Python :: 3.12
Classifier: Topic :: Internet :: WWW/HTTP
Classifier: Topic :: Internet :: WWW/HTTP :: Dynamic Content
Classifier: Topic :: Software Development :: Libraries :: Python Modules
Classifier: Framework :: Paste
Requires-Python: >=3.7
License-File: AUTHORS
Requires-Dist: Paste>=3.0
Requires-Dist: PasteDeploy
Requires-Dist: setuptools
Provides-Extra: templating
Provides-Extra: cheetah
Requires-Dist: Cheetah; extra == "cheetah"
Provides-Extra: config
Requires-Dist: PasteDeploy; extra == "config"
Provides-Extra: wsgiutils
Requires-Dist: WSGIserver; extra == "wsgiutils"
Provides-Extra: flup
Requires-Dist: Flup; extra == "flup"
Provides-Extra: paste
Requires-Dist: PasteDeploy; extra == "paste"
Requires-Dist: Cheetah; extra == "paste"
